LICENSE
README.md
setup.py
kutin_synthesis_plugin_for_qiskit.egg-info/PKG-INFO
kutin_synthesis_plugin_for_qiskit.egg-info/SOURCES.txt
kutin_synthesis_plugin_for_qiskit.egg-info/dependency_links.txt
kutin_synthesis_plugin_for_qiskit.egg-info/entry_points.txt
kutin_synthesis_plugin_for_qiskit.egg-info/requires.txt
kutin_synthesis_plugin_for_qiskit.egg-info/top_level.txt
qiskit_kutin_synthesis/__init__.py
qiskit_kutin_synthesis/binary_matrix_utils.py
qiskit_kutin_synthesis/examples.py
qiskit_kutin_synthesis/kutin_synthesis.py
qiskit_kutin_synthesis/kutin_synthesis_plugin.py